HonghuLuntanCcna640802KechengJiangyiFix1/README.md
HonghuLuntanCcna640802KechengJiangyiFix1/__init__.py
HonghuLuntanCcna640802KechengJiangyiFix1/__main__.py
HonghuLuntanCcna640802KechengJiangyiFix1/file.pdf
HonghuLuntanCcna640802KechengJiangyiFix1/index.html
honghu_luntan_ccna_640_802_kecheng_jiangyi_fix1-2025.3.25.1.dist-info/METADATA
honghu_luntan_ccna_640_802_kecheng_jiangyi_fix1-2025.3.25.1.dist-info/WHEEL
honghu_luntan_ccna_640_802_kecheng_jiangyi_fix1-2025.3.25.1.dist-info/entry_points.txt
honghu_luntan_ccna_640_802_kecheng_jiangyi_fix1-2025.3.25.1.dist-info/top_level.txt
honghu_luntan_ccna_640_802_kecheng_jiangyi_fix1-2025.3.25.1.dist-info/RECORD
